<?xml version = '1.0' encoding = 'UTF-8'?>
<Diagram class="oracle.dbtools.crest.swingui.relational.DPVRelational" name="Relational_1" id="C883EAA7-4B8A-3C61-5781-AB8DE93BA42D">
<createdBy>mesoi</createdBy>
<modifiedBy>mesoi</modifiedBy>
<createdTime>2024-09-13 04:40:20 UTC</createdTime>
<autoRoute>false</autoRoute>
<boxInbox>true</boxInbox>
<showLegend>false</showLegend>
<showLabels>false</showLabels>
<showRelAttributes>false</showRelAttributes>
<gridEnabled>false</gridEnabled>
<showGrid>false</showGrid>
<diagramColor>-1</diagramColor>
<display>false</display>
<notation>1</notation>
<objectViews>
<OView class="oracle.dbtools.crest.swingui.relational.TVTable" oid="1ADAD43A-6347-D540-02CE-8D3E452451A9" otype="Table" vid="D03C3BC0-2826-6E58-6A43-39AA37B4E654">
<hideElementsInCurrentOnly>false</hideElementsInCurrentOnly>
<bounds x="573" y="261" width="204" height="100"/>
</OView>
<OView class="oracle.dbtools.crest.swingui.relational.TVTable" oid="1B89FDF5-B8B7-735F-1853-7B2F69E38BCA" otype="Table" vid="42CFCBF3-CBF0-70D4-0168-035BE2E54389">
<hideElementsInCurrentOnly>false</hideElementsInCurrentOnly>
<bounds x="1237" y="200" width="221" height="116"/>
</OView>
<OView class="oracle.dbtools.crest.swingui.relational.TVTable" oid="1C31C1D6-2F90-925F-D845-EB9071FCC562" otype="Table" vid="EFE84525-E03A-73BD-0DA1-FAFF8265D099">
<hideElementsInCurrentOnly>false</hideElementsInCurrentOnly>
<bounds x="786" y="357" width="400" height="206"/>
</OView>
<OView class="oracle.dbtools.crest.swingui.relational.TVTable" oid="1DBB7462-9D38-1DE8-2C61-9DE50DF32CC3" otype="Table" vid="1A344035-58F1-8B53-E1DF-44A11664AA07">
<hideElementsInCurrentOnly>false</hideElementsInCurrentOnly>
<bounds x="921" y="763" width="297" height="163"/>
</OView>
<OView class="oracle.dbtools.crest.swingui.relational.TVTable" oid="21B344B4-E66D-55B2-3490-CE12CD2DCFB7" otype="Table" vid="DF3FE760-E766-35FC-9BFC-1D36E18C337C">
<hideElementsInCurrentOnly>false</hideElementsInCurrentOnly>
<bounds x="582" y="460" width="170" height="112"/>
</OView>
<OView class="oracle.dbtools.crest.swingui.relational.TVTable" oid="30285F9A-7703-B126-4BBB-76C4A39E2CBF" otype="Table" vid="62E2C28F-9FB6-B6BA-2345-9CC2CCA1F308">
<hideElementsInCurrentOnly>false</hideElementsInCurrentOnly>
<bounds x="558" y="696" width="341" height="180"/>
</OView>
<OView class="oracle.dbtools.crest.swingui.relational.TVTable" oid="3D8BDE81-1B88-A891-7F66-ECB39E522FA5" otype="Table" vid="7AE6B3DE-2362-DD29-6EAC-4595CB53CC18">
<hideElementsInCurrentOnly>false</hideElementsInCurrentOnly>
<bounds x="733" y="988" width="297" height="110"/>
</OView>
<OView class="oracle.dbtools.crest.swingui.relational.TVTable" oid="41A53F0C-210C-337C-001C-23BED4E7C835" otype="Table" vid="56CBF923-4C8C-7355-FFD4-D9FB85749583">
<hideElementsInCurrentOnly>false</hideElementsInCurrentOnly>
<bounds x="1199" y="17" width="362" height="116"/>
</OView>
<OView class="oracle.dbtools.crest.swingui.relational.TVTable" oid="47C35688-0898-87E8-6F3B-25362B709147" otype="Table" vid="7B58694F-C914-7FF7-7496-DCA989F2E9F6">
<hideElementsInCurrentOnly>false</hideElementsInCurrentOnly>
<bounds x="1377" y="369" width="248" height="142"/>
</OView>
<OView class="oracle.dbtools.crest.swingui.relational.TVTable" oid="48737662-CBD3-C439-B0E1-3D1B78148BE3" otype="Table" vid="0606102F-60F0-AE5C-0E8F-F766B4F1C76B">
<hideElementsInCurrentOnly>false</hideElementsInCurrentOnly>
<bounds x="91" y="907" width="187" height="110"/>
</OView>
<OView class="oracle.dbtools.crest.swingui.relational.TVTable" oid="54386E8F-443A-21DA-3F0F-E0B46A7EBDC0" otype="Table" vid="9A626521-0175-1189-A83D-FF138C6E82F9">
<hideElementsInCurrentOnly>false</hideElementsInCurrentOnly>
<bounds x="263" y="723" width="239" height="113"/>
</OView>
<OView class="oracle.dbtools.crest.swingui.relational.TVTable" oid="6024D6F9-05E6-3BB0-81E7-5E6B59AAD326" otype="Table" vid="EA02839E-7B2B-447C-EF3F-989E0C868B9C">
<hideElementsInCurrentOnly>false</hideElementsInCurrentOnly>
<bounds x="414" y="911" width="272" height="110"/>
</OView>
<OView class="oracle.dbtools.crest.swingui.relational.TVTable" oid="73589945-A802-BE5E-1E2B-CE0553B89E8F" otype="Table" vid="65DEB656-F632-4DE0-77E1-2DACFB78DD0A">
<hideElementsInCurrentOnly>false</hideElementsInCurrentOnly>
<bounds x="1094" y="595" width="231" height="110"/>
</OView>
<OView class="oracle.dbtools.crest.swingui.relational.TVTable" oid="A7304632-EA2F-DF9C-E68E-8064EC9D36D3" otype="Table" vid="6564F3D6-A50A-B891-9F33-FA4B8099C573">
<hideElementsInCurrentOnly>false</hideElementsInCurrentOnly>
<bounds x="4" y="258" width="340" height="118"/>
</OView>
<OView class="oracle.dbtools.crest.swingui.relational.TVTable" oid="A7CE56A1-C1FF-FFC0-0F6B-68A04807B096" otype="Table" vid="DEC91D32-D074-5B70-D8E5-5B6C7853F9D0">
<hideElementsInCurrentOnly>false</hideElementsInCurrentOnly>
<bounds x="2" y="498" width="331" height="179"/>
</OView>
<OView class="oracle.dbtools.crest.swingui.relational.TVTable" oid="AE2A3CB6-0948-6130-FD98-7C4B358A002E" otype="Table" vid="F1C6C2AD-1B05-357A-D20C-3A66762FBFE0">
<hideElementsInCurrentOnly>false</hideElementsInCurrentOnly>
<bounds x="0" y="11" width="300" height="150"/>
</OView>
<OView class="oracle.dbtools.crest.swingui.relational.TVTable" oid="B13519A3-1904-A589-2333-FF623A49CB21" otype="Table" vid="F441D395-3F70-A964-42CE-6B3A19A3BC1F">
<hideElementsInCurrentOnly>false</hideElementsInCurrentOnly>
<bounds x="302" y="1" width="358" height="111"/>
</OView>
<OView class="oracle.dbtools.crest.swingui.relational.TVTable" oid="B344978D-DF67-1D55-27B9-25C932D7CC5E" otype="Table" vid="7E3E966B-7F0C-1F84-BBD2-01969C339BC3">
<hideElementsInCurrentOnly>false</hideElementsInCurrentOnly>
<bounds x="371" y="234" width="170" height="154"/>
</OView>
<OView class="oracle.dbtools.crest.swingui.relational.TVTable" oid="B60D03F2-63E7-C6EC-4C5F-DB1CB2B369FA" otype="Table" vid="C2082074-B4D5-9D67-58A8-4E5364E0097C">
<hideElementsInCurrentOnly>false</hideElementsInCurrentOnly>
<bounds x="589" y="149" width="193" height="87"/>
</OView>
<OView class="oracle.dbtools.crest.swingui.relational.TVTable" oid="D91D9AAA-56EE-5B41-1237-81EBE3D844CA" otype="Table" vid="F3411659-267A-771C-E9A7-C4A209C6F2F6">
<hideElementsInCurrentOnly>false</hideElementsInCurrentOnly>
<bounds x="374" y="507" width="170" height="116"/>
</OView>
<OView class="oracle.dbtools.crest.swingui.relational.TVTable" oid="DE0D6A47-F7EB-2F50-D8C1-A9F84ECD7EF7" otype="Table" vid="3E758C53-D886-7A4C-6B48-7FC318B2389D">
<hideElementsInCurrentOnly>false</hideElementsInCurrentOnly>
<bounds x="923" y="52" width="239" height="95"/>
</OView>
<OView class="oracle.dbtools.crest.swingui.relational.TVTable" oid="E940CAA1-C2F4-7B28-4EB8-EEEBBCB2B23A" otype="Table" vid="2726D1A4-B54C-7378-C0A2-1EE30772C5C6">
<hideElementsInCurrentOnly>false</hideElementsInCurrentOnly>
<bounds x="690" y="0" width="208" height="113"/>
</OView>
<OView class="oracle.dbtools.crest.swingui.relational.TVTable" oid="EDE728F9-D85D-1A9A-33EB-2BE19648EF4B" otype="Table" vid="A6DA7A69-1C41-73F0-8158-0D4E8DFACC1D">
<hideElementsInCurrentOnly>false</hideElementsInCurrentOnly>
<bounds x="5" y="736" width="239" height="119"/>
</OView>
<OView class="oracle.dbtools.crest.swingui.relational.TVTable" oid="FDC42183-3221-E56D-2B3B-D1111BFA5192" otype="Table" vid="E13000DE-5CF2-469B-B3E1-BBDB2637E39F">
<hideElementsInCurrentOnly>false</hideElementsInCurrentOnly>
<bounds x="1280" y="720" width="170" height="114"/>
</OView>
</objectViews>
<connectors>
<Connector class="oracle.dbtools.crest.swingui.relational.TVFKRelation" oid="0DFA0F86-2C1C-4B09-6D25-09676E59DEAF" otype="FKIndexAssociation" vid_source="65DEB656-F632-4DE0-77E1-2DACFB78DD0A" vid_target="EFE84525-E03A-73BD-0DA1-FAFF8265D099">
<hideElementsInCurrentOnly>false</hideElementsInCurrentOnly>
<backgroundColor>-16777216</backgroundColor>
<lineWidth>1</lineWidth>
<points>
<point x="1140" y="595"/>
<point x="1140" y="563"/>
</points>
</Connector>
<Connector class="oracle.dbtools.crest.swingui.relational.TVFKRelation" oid="21330415-1152-2B51-E676-B62BEBBCEC5D" otype="FKIndexAssociation" vid_source="A6DA7A69-1C41-73F0-8158-0D4E8DFACC1D" vid_target="DEC91D32-D074-5B70-D8E5-5B6C7853F9D0">
<hideElementsInCurrentOnly>false</hideElementsInCurrentOnly>
<backgroundColor>-16777216</backgroundColor>
<lineWidth>1</lineWidth>
<points>
<point x="124" y="736"/>
<point x="124" y="677"/>
</points>
</Connector>
<Connector class="oracle.dbtools.crest.swingui.relational.TVFKRelation" oid="26B030AB-1198-41DA-9F33-790546A125B0" otype="FKIndexAssociation" vid_source="DF3FE760-E766-35FC-9BFC-1D36E18C337C" vid_target="62E2C28F-9FB6-B6BA-2345-9CC2CCA1F308">
<hideElementsInCurrentOnly>false</hideElementsInCurrentOnly>
<backgroundColor>-16777216</backgroundColor>
<lineWidth>1</lineWidth>
<points>
<point x="682" y="572"/>
<point x="682" y="696"/>
</points>
</Connector>
<Connector class="oracle.dbtools.crest.swingui.relational.TVFKRelation" oid="3B821C2E-F9A8-85BB-DACA-8F9F698CCE0F" otype="FKIndexAssociation" vid_source="42CFCBF3-CBF0-70D4-0168-035BE2E54389" vid_target="EFE84525-E03A-73BD-0DA1-FAFF8265D099">
<hideElementsInCurrentOnly>false</hideElementsInCurrentOnly>
<backgroundColor>-16777216</backgroundColor>
<lineWidth>1</lineWidth>
<points>
<point x="1243" y="316"/>
<point x="1170" y="357"/>
</points>
</Connector>
<Connector class="oracle.dbtools.crest.swingui.relational.TVFKRelation" oid="45E80DD8-1F16-2C8B-001E-63E5BC7BB63E" otype="FKIndexAssociation" vid_source="F3411659-267A-771C-E9A7-C4A209C6F2F6" vid_target="DF3FE760-E766-35FC-9BFC-1D36E18C337C">
<hideElementsInCurrentOnly>false</hideElementsInCurrentOnly>
<backgroundColor>-16777216</backgroundColor>
<lineWidth>1</lineWidth>
<points>
<point x="544" y="539"/>
<point x="582" y="539"/>
</points>
</Connector>
<Connector class="oracle.dbtools.crest.swingui.relational.TVFKRelation" oid="4F171E73-D51E-3C1D-F3B4-3E168A8B5337" otype="FKIndexAssociation" vid_source="1A344035-58F1-8B53-E1DF-44A11664AA07" vid_target="7AE6B3DE-2362-DD29-6EAC-4595CB53CC18">
<hideElementsInCurrentOnly>false</hideElementsInCurrentOnly>
<backgroundColor>-16777216</backgroundColor>
<lineWidth>1</lineWidth>
<points>
<point x="975" y="926"/>
<point x="975" y="988"/>
</points>
</Connector>
<Connector class="oracle.dbtools.crest.swingui.relational.TVFKRelation" oid="59D3D135-10C7-9B26-54FA-3BDE09DA0D62" otype="FKIndexAssociation" vid_source="3E758C53-D886-7A4C-6B48-7FC318B2389D" vid_target="EFE84525-E03A-73BD-0DA1-FAFF8265D099">
<hideElementsInCurrentOnly>false</hideElementsInCurrentOnly>
<backgroundColor>-16777216</backgroundColor>
<lineWidth>1</lineWidth>
<points>
<point x="1042" y="147"/>
<point x="1042" y="357"/>
</points>
</Connector>
<Connector class="oracle.dbtools.crest.swingui.relational.TVFKRelation" oid="68092A66-788F-A5FE-10AE-AF6A757B8D67" otype="FKIndexAssociation" vid_source="E13000DE-5CF2-469B-B3E1-BBDB2637E39F" vid_target="1A344035-58F1-8B53-E1DF-44A11664AA07">
<hideElementsInCurrentOnly>false</hideElementsInCurrentOnly>
<backgroundColor>-16777216</backgroundColor>
<lineWidth>1</lineWidth>
<points>
<point x="1280" y="798"/>
<point x="1218" y="798"/>
</points>
</Connector>
<Connector class="oracle.dbtools.crest.swingui.relational.TVFKRelation" oid="6B14B45C-FB2E-5EFD-23BB-49D7C8537F71" otype="FKIndexAssociation" vid_source="EFE84525-E03A-73BD-0DA1-FAFF8265D099" vid_target="7B58694F-C914-7FF7-7496-DCA989F2E9F6">
<hideElementsInCurrentOnly>false</hideElementsInCurrentOnly>
<backgroundColor>-16777216</backgroundColor>
<lineWidth>1</lineWidth>
<points>
<point x="1186" y="440"/>
<point x="1377" y="440"/>
</points>
</Connector>
<Connector class="oracle.dbtools.crest.swingui.relational.TVFKRelation" oid="8C709036-E838-C48A-EAE6-5538A27F6B92" otype="FKIndexAssociation" vid_source="EFE84525-E03A-73BD-0DA1-FAFF8265D099" vid_target="7B58694F-C914-7FF7-7496-DCA989F2E9F6">
<hideElementsInCurrentOnly>false</hideElementsInCurrentOnly>
<backgroundColor>-16777216</backgroundColor>
<lineWidth>1</lineWidth>
<points>
<point x="1186" y="455"/>
<point x="1377" y="455"/>
</points>
</Connector>
<Connector class="oracle.dbtools.crest.swingui.relational.TVFKRelation" oid="8D2F4873-3625-19DA-BC40-F6B379AF3857" otype="FKIndexAssociation" vid_source="DEC91D32-D074-5B70-D8E5-5B6C7853F9D0" vid_target="6564F3D6-A50A-B891-9F33-FA4B8099C573">
<hideElementsInCurrentOnly>false</hideElementsInCurrentOnly>
<backgroundColor>-16777216</backgroundColor>
<lineWidth>1</lineWidth>
<points>
<point x="168" y="498"/>
<point x="168" y="376"/>
</points>
</Connector>
<Connector class="oracle.dbtools.crest.swingui.relational.TVFKRelation" oid="9345EA7A-8D67-7DD4-DF2B-EE9DC6A3BA21" otype="FKIndexAssociation" vid_source="F3411659-267A-771C-E9A7-C4A209C6F2F6" vid_target="DEC91D32-D074-5B70-D8E5-5B6C7853F9D0">
<hideElementsInCurrentOnly>false</hideElementsInCurrentOnly>
<backgroundColor>-16777216</backgroundColor>
<lineWidth>1</lineWidth>
<points>
<point x="374" y="565"/>
<point x="333" y="565"/>
</points>
</Connector>
<Connector class="oracle.dbtools.crest.swingui.relational.TVFKRelation" oid="9607AF92-9B1B-0E82-77E1-207C2A45BE73" otype="FKIndexAssociation" vid_source="7E3E966B-7F0C-1F84-BBD2-01969C339BC3" vid_target="F1C6C2AD-1B05-357A-D20C-3A66762FBFE0">
<hideElementsInCurrentOnly>false</hideElementsInCurrentOnly>
<backgroundColor>-16777216</backgroundColor>
<lineWidth>1</lineWidth>
<points>
<point x="371" y="248"/>
<point x="252" y="161"/>
</points>
</Connector>
<Connector class="oracle.dbtools.crest.swingui.relational.TVFKRelation" oid="9F875F0C-1182-DD2B-3A7A-DFEFCE38FC40" otype="FKIndexAssociation" vid_source="F3411659-267A-771C-E9A7-C4A209C6F2F6" vid_target="7E3E966B-7F0C-1F84-BBD2-01969C339BC3">
<hideElementsInCurrentOnly>false</hideElementsInCurrentOnly>
<backgroundColor>-16777216</backgroundColor>
<lineWidth>1</lineWidth>
<points>
<point x="457" y="507"/>
<point x="457" y="388"/>
</points>
</Connector>
<Connector class="oracle.dbtools.crest.swingui.relational.TVFKRelation" oid="B01EB046-2CC2-CD92-0ABC-18B6A5AA7961" otype="FKIndexAssociation" vid_source="D03C3BC0-2826-6E58-6A43-39AA37B4E654" vid_target="DF3FE760-E766-35FC-9BFC-1D36E18C337C">
<hideElementsInCurrentOnly>false</hideElementsInCurrentOnly>
<backgroundColor>-16777216</backgroundColor>
<lineWidth>1</lineWidth>
<points>
<point x="667" y="361"/>
<point x="667" y="460"/>
</points>
</Connector>
<Connector class="oracle.dbtools.crest.swingui.relational.TVFKRelation" oid="C918D682-418B-39CA-CBB1-AAD5268CA9A3" otype="FKIndexAssociation" vid_source="42CFCBF3-CBF0-70D4-0168-035BE2E54389" vid_target="1A344035-58F1-8B53-E1DF-44A11664AA07">
<hideElementsInCurrentOnly>false</hideElementsInCurrentOnly>
<backgroundColor>-16777216</backgroundColor>
<lineWidth>1</lineWidth>
<points>
<point x="1320" y="316"/>
<point x="1108" y="763"/>
</points>
</Connector>
<Connector class="oracle.dbtools.crest.swingui.relational.TVFKRelation" oid="D240A62B-12A1-CCB4-00EF-7E0F6EFD3DF0" otype="FKIndexAssociation" vid_source="9A626521-0175-1189-A83D-FF138C6E82F9" vid_target="62E2C28F-9FB6-B6BA-2345-9CC2CCA1F308">
<hideElementsInCurrentOnly>false</hideElementsInCurrentOnly>
<backgroundColor>-16777216</backgroundColor>
<lineWidth>1</lineWidth>
<points>
<point x="502" y="779"/>
<point x="558" y="779"/>
</points>
</Connector>
<Connector class="oracle.dbtools.crest.swingui.relational.TVFKRelation" oid="D5111FEF-EF02-6FCD-3A4C-5C06BD21D633" otype="FKIndexAssociation" vid_source="0606102F-60F0-AE5C-0E8F-F766B4F1C76B" vid_target="EA02839E-7B2B-447C-EF3F-989E0C868B9C">
<hideElementsInCurrentOnly>false</hideElementsInCurrentOnly>
<backgroundColor>-16777216</backgroundColor>
<lineWidth>1</lineWidth>
<points>
<point x="278" y="979"/>
<point x="414" y="979"/>
</points>
</Connector>
<Connector class="oracle.dbtools.crest.swingui.relational.TVFKRelation" oid="D74C963F-08A3-5AA8-202E-98901A397E3A" otype="FKIndexAssociation" vid_source="42CFCBF3-CBF0-70D4-0168-035BE2E54389" vid_target="56CBF923-4C8C-7355-FFD4-D9FB85749583">
<hideElementsInCurrentOnly>false</hideElementsInCurrentOnly>
<backgroundColor>-16777216</backgroundColor>
<lineWidth>1</lineWidth>
<points>
<point x="1347" y="200"/>
<point x="1347" y="133"/>
</points>
</Connector>
<Connector class="oracle.dbtools.crest.swingui.relational.TVFKRelation" oid="DDF7FF5B-8054-11CC-AD78-076632F7632A" otype="FKIndexAssociation" vid_source="2726D1A4-B54C-7378-C0A2-1EE30772C5C6" vid_target="EFE84525-E03A-73BD-0DA1-FAFF8265D099">
<hideElementsInCurrentOnly>false</hideElementsInCurrentOnly>
<backgroundColor>-16777216</backgroundColor>
<lineWidth>1</lineWidth>
<points>
<point x="857" y="113"/>
<point x="857" y="357"/>
</points>
</Connector>
<Connector class="oracle.dbtools.crest.swingui.relational.TVFKRelation" oid="E080D049-7829-220D-74B4-A200E4C72E0D" otype="FKIndexAssociation" vid_source="7E3E966B-7F0C-1F84-BBD2-01969C339BC3" vid_target="F441D395-3F70-A964-42CE-6B3A19A3BC1F">
<hideElementsInCurrentOnly>false</hideElementsInCurrentOnly>
<backgroundColor>-16777216</backgroundColor>
<lineWidth>1</lineWidth>
<points>
<point x="456" y="234"/>
<point x="456" y="112"/>
</points>
</Connector>
<Connector class="oracle.dbtools.crest.swingui.relational.TVFKRelation" oid="F251E12B-AB68-763F-384C-D3E115B7AA5A" otype="FKIndexAssociation" vid_source="C2082074-B4D5-9D67-58A8-4E5364E0097C" vid_target="7E3E966B-7F0C-1F84-BBD2-01969C339BC3">
<hideElementsInCurrentOnly>false</hideElementsInCurrentOnly>
<backgroundColor>-16777216</backgroundColor>
<lineWidth>1</lineWidth>
<points>
<point x="589" y="235"/>
<point x="541" y="235"/>
</points>
</Connector>
<Connector class="oracle.dbtools.crest.swingui.relational.TVFKRelation" oid="F57C2705-762C-F2E8-AAA6-ADB2904E8537" otype="FKIndexAssociation" vid_source="62E2C28F-9FB6-B6BA-2345-9CC2CCA1F308" vid_target="7AE6B3DE-2362-DD29-6EAC-4595CB53CC18">
<hideElementsInCurrentOnly>false</hideElementsInCurrentOnly>
<backgroundColor>-16777216</backgroundColor>
<lineWidth>1</lineWidth>
<points>
<point x="816" y="876"/>
<point x="816" y="988"/>
</points>
</Connector>
<Connector class="oracle.dbtools.crest.swingui.relational.TVFKRelation" oid="FB0CEAAA-A01B-D2A3-B15B-F27EB094F99B" otype="FKIndexAssociation" vid_source="EFE84525-E03A-73BD-0DA1-FAFF8265D099" vid_target="1A344035-58F1-8B53-E1DF-44A11664AA07">
<hideElementsInCurrentOnly>false</hideElementsInCurrentOnly>
<backgroundColor>-16777216</backgroundColor>
<lineWidth>1</lineWidth>
<points>
<point x="1053" y="563"/>
<point x="1053" y="763"/>
</points>
</Connector>
</connectors>
</Diagram>
