<?xml version = '1.0' encoding = 'UTF-8'?>
<Relation class="oracle.dbtools.crest.model.design.logical.Relation" name="Relation_14" directorySegmentName="seg_0" id="34D609D3-16D3-EBF3-0750-19770736BAD1">
<createdBy>mesoi</createdBy>
<createdTime>2024-09-13 04:33:09 UTC</createdTime>
<ownerDesignName>DB_G13</ownerDesignName>
<engineerTo>
<item key="961B8C99-B512-7E8A-0731-14A4EBE42F8B" value="true"/>
</engineerTo>
<sourcePk>406BCBA2-09D9-636C-E032-3362AD415EA2</sourcePk>
<identifying>false</identifying>
<nameOnSource>pertenece</nameOnSource>
<nameOnTarget>tiene</nameOnTarget>
<optionalSource>true</optionalSource>
<optionalTarget>false</optionalTarget>
<sourceCardinality>1</sourceCardinality>
<sourceEntity>0312EE8D-96CE-B771-0D85-FE36923C6776</sourceEntity>
<targetCardinalityString>1</targetCardinalityString>
<targetEntity>AE0BE0F2-6DAF-530E-2E7C-A04B98177177</targetEntity>
<transferable>true</transferable>
<deleteRule>NO ACTION</deleteRule>
</Relation>
